setup.py
dcnmtoolkit/__about__.py
dcnmtoolkit/__init__.py
dcnmtoolkit/autoconfig.py
dcnmtoolkit/cableplan.py
dcnmtoolkit/config.py
dcnmtoolkit/dcnmsession.py
dcnmtoolkit/poap.py
dcnmtoolkit/vxlan.py
dcnmtoolkit.egg-info/PKG-INFO
dcnmtoolkit.egg-info/SOURCES.txt
dcnmtoolkit.egg-info/dependency_links.txt
dcnmtoolkit.egg-info/requires.txt
dcnmtoolkit.egg-info/top_level.txt