Metadata-Version: 1.0
Name: dcnmtoolkit
Version: 0.0.1
Summary: This library allows basic Cisco DCNM configuration.
Home-page: http://github.com/kecorbin/dcnmtoolkit/
Author: Cisco Systems, Inc.
Author-email: kecorbin@cisco.com
License: Apache License, Version 2.0
Platform: UNKNOWN
